ipeds_wrangler/__init__.py
ipeds_wrangler/download_ipeds_databases.py
ipeds_wrangler/parse_ipeds_databases.py
ipeds_wrangler-0.0.5.dist-info/licenses/LICENSE
ipeds_wrangler-0.0.5.dist-info/METADATA
ipeds_wrangler-0.0.5.dist-info/WHEEL
ipeds_wrangler-0.0.5.dist-info/top_level.txt
ipeds_wrangler-0.0.5.dist-info/RECORD
