Metadata-Version: 2.4
Name: ipeds_wrangler
Version: 0.0.5
Summary: A package for wrangling IPEDS data
Author-email: Tracy Reuter <tracy.ellen.reuter@gmail.com>
License-Expression: MIT
Project-URL: Homepage, https://github.com/tracyreuter/ipeds-wrangler
Classifier: Programming Language :: Python :: 3
Classifier: Operating System :: OS Independent
Requires-Python: >=3.13
License-File: LICENSE
Dynamic: license-file
